{"cameraMode":{"drawMode":0,"name":"Shaded","section":"Shading Mode"},"sceneLighting":true,"audioPlay":false,"sceneViewState":{"m_AlwaysRefresh":false,"showFog":true,"showSkybox":true,"showFlares":true,"showImageEffects":true,"showParticleSystems":true,"showVisualEffectGraphs":true,"m_FxEnabled":true},"in2DMode":false,"pivot":{"x":0.0,"y":22.380603790283204,"z":-333.0},"rotation":{"x":0.010793719440698624,"y":-0.9883242845535278,"z":0.12669673562049867,"w":0.0841054767370224},"size":410.841552734375,"orthographic":false}