{"cameraMode":{"drawMode":0,"name":"Shaded","section":"Shading Mode"},"sceneLighting":true,"audioPlay":false,"sceneViewState":{"m_AlwaysRefresh":false,"showFog":true,"showSkybox":true,"showFlares":true,"showImageEffects":true,"showParticleSystems":true,"showVisualEffectGraphs":true,"m_FxEnabled":true},"in2DMode":false,"pivot":{"x":19.907997131347658,"y":-39.909767150878909,"z":469.0982360839844},"rotation":{"x":0.23536230623722077,"y":-0.4358919560909271,"z":0.11923036724328995,"w":0.8604597449302673},"size":29.650421142578126,"orthographic":false}